<annotation><folder>Tomato_Village_resized 640x640/train/pascal_voc</folder><filename>IMG20220324085244_aug4.jpg</filename><path>./imagesIMG20220324085244_aug4.jpg</path><source><database>Unknown</database></source><size><width>640</width><height>640</height><depth>3</depth></size><segmented>0</segmented><object><name>7.0</name><pose>Unspecified</pose><truncated>0</truncated><difficult>0</difficult><bndbox><xmin>271</xmin><ymin>423</ymin><xmax>489</xmax><ymax>540</ymax></bndbox></object><object><name>7.0</name><pose>Unspecified</pose><truncated>0</truncated><difficult>0</difficult><bndbox><xmin>282</xmin><ymin>267</ymin><xmax>449</xmax><ymax>395</ymax></bndbox></object><object><name>7.0</name><pose>Unspecified</pose><truncated>0</truncated><difficult>0</difficult><bndbox><xmin>486</xmin><ymin>286</ymin><xmax>594</xmax><ymax>487</ymax></bndbox></object><object><name>7.0</name><pose>Unspecified</pose><truncated>0</truncated><difficult>0</difficult><bndbox><xmin>65</xmin><ymin>400</ymin><xmax>231</xmax><ymax>517</ymax></bndbox></object><object><name>7.0</name><pose>Unspecified</pose><truncated>0</truncated><difficult>0</difficult><bndbox><xmin>0</xmin><ymin>239</ymin><xmax>111</xmax><ymax>342</ymax></bndbox></object><object><name>3.0</name><pose>Unspecified</pose><truncated>0</truncated><difficult>0</difficult><bndbox><xmin>436</xmin><ymin>3</ymin><xmax>516</xmax><ymax>48</ymax></bndbox></object><object><name>7.0</name><pose>Unspecified</pose><truncated>0</truncated><difficult>0</difficult><bndbox><xmin>585</xmin><ymin>121</ymin><xmax>634</xmax><ymax>156</ymax></bndbox></object></annotation>