<annotation><folder>Tomato_Village_resized 640x640/train/pascal_voc</folder><filename>IMG20220325091145_aug7.jpg</filename><path>./imagesIMG20220325091145_aug7.jpg</path><source><database>Unknown</database></source><size><width>640</width><height>640</height><depth>3</depth></size><segmented>0</segmented><object><name>4.0</name><pose>Unspecified</pose><truncated>0</truncated><difficult>0</difficult><bndbox><xmin>81</xmin><ymin>386</ymin><xmax>434</xmax><ymax>495</ymax></bndbox></object><object><name>4.0</name><pose>Unspecified</pose><truncated>0</truncated><difficult>0</difficult><bndbox><xmin>0</xmin><ymin>352</ymin><xmax>237</xmax><ymax>461</ymax></bndbox></object><object><name>4.0</name><pose>Unspecified</pose><truncated>0</truncated><difficult>0</difficult><bndbox><xmin>345</xmin><ymin>494</ymin><xmax>565</xmax><ymax>640</ymax></bndbox></object><object><name>4.0</name><pose>Unspecified</pose><truncated>0</truncated><difficult>0</difficult><bndbox><xmin>87</xmin><ymin>590</ymin><xmax>288</xmax><ymax>640</ymax></bndbox></object><object><name>3.0</name><pose>Unspecified</pose><truncated>0</truncated><difficult>0</difficult><bndbox><xmin>125</xmin><ymin>617</ymin><xmax>176</xmax><ymax>640</ymax></bndbox></object><object><name>3.0</name><pose>Unspecified</pose><truncated>0</truncated><difficult>0</difficult><bndbox><xmin>421</xmin><ymin>545</ymin><xmax>520</xmax><ymax>638</ymax></bndbox></object><object><name>3.0</name><pose>Unspecified</pose><truncated>0</truncated><difficult>0</difficult><bndbox><xmin>0</xmin><ymin>383</ymin><xmax>65</xmax><ymax>432</ymax></bndbox></object><object><name>3.0</name><pose>Unspecified</pose><truncated>0</truncated><difficult>0</difficult><bndbox><xmin>94</xmin><ymin>416</ymin><xmax>191</xmax><ymax>482</ymax></bndbox></object><object><name>3.0</name><pose>Unspecified</pose><truncated>0</truncated><difficult>0</difficult><bndbox><xmin>205</xmin><ymin>427</ymin><xmax>389</xmax><ymax>489</ymax></bndbox></object><object><name>4.0</name><pose>Unspecified</pose><truncated>0</truncated><difficult>0</difficult><bndbox><xmin>24</xmin><ymin>0</ymin><xmax>366</xmax><ymax>151</ymax></bndbox></object><object><name>3.0</name><pose>Unspecified</pose><truncated>0</truncated><difficult>0</difficult><bndbox><xmin>0</xmin><ymin>0</ymin><xmax>63</xmax><ymax>23</ymax></bndbox></object><object><name>3.0</name><pose>Unspecified</pose><truncated>0</truncated><difficult>0</difficult><bndbox><xmin>180</xmin><ymin>9</ymin><xmax>337</xmax><ymax>97</ymax></bndbox></object></annotation>