<annotation><folder>Tomato_Village_resized 640x640/train/pascal_voc</folder><filename>IMG20220325091247_aug3.jpg</filename><path>./imagesIMG20220325091247_aug3.jpg</path><source><database>Unknown</database></source><size><width>640</width><height>640</height><depth>3</depth></size><segmented>0</segmented><object><name>3.0</name><pose>Unspecified</pose><truncated>0</truncated><difficult>0</difficult><bndbox><xmin>498</xmin><ymin>102</ymin><xmax>575</xmax><ymax>168</ymax></bndbox></object><object><name>3.0</name><pose>Unspecified</pose><truncated>0</truncated><difficult>0</difficult><bndbox><xmin>559</xmin><ymin>111</ymin><xmax>640</xmax><ymax>197</ymax></bndbox></object><object><name>3.0</name><pose>Unspecified</pose><truncated>0</truncated><difficult>0</difficult><bndbox><xmin>6</xmin><ymin>263</ymin><xmax>38</xmax><ymax>293</ymax></bndbox></object><object><name>3.0</name><pose>Unspecified</pose><truncated>0</truncated><difficult>0</difficult><bndbox><xmin>207</xmin><ymin>326</ymin><xmax>251</xmax><ymax>348</ymax></bndbox></object></annotation>