<annotation><folder>Tomato_Village_resized 640x640/train/pascal_voc</folder><filename>IMG20220325092922_aug4.jpg</filename><path>./imagesIMG20220325092922_aug4.jpg</path><source><database>Unknown</database></source><size><width>640</width><height>640</height><depth>3</depth></size><segmented>0</segmented><object><name>3.0</name><pose>Unspecified</pose><truncated>0</truncated><difficult>0</difficult><bndbox><xmin>85</xmin><ymin>404</ymin><xmax>149</xmax><ymax>473</ymax></bndbox></object><object><name>3.0</name><pose>Unspecified</pose><truncated>0</truncated><difficult>0</difficult><bndbox><xmin>212</xmin><ymin>374</ymin><xmax>232</xmax><ymax>436</ymax></bndbox></object><object><name>3.0</name><pose>Unspecified</pose><truncated>0</truncated><difficult>0</difficult><bndbox><xmin>328</xmin><ymin>508</ymin><xmax>355</xmax><ymax>558</ymax></bndbox></object><object><name>3.0</name><pose>Unspecified</pose><truncated>0</truncated><difficult>0</difficult><bndbox><xmin>333</xmin><ymin>232</ymin><xmax>355</xmax><ymax>287</ymax></bndbox></object><object><name>3.0</name><pose>Unspecified</pose><truncated>0</truncated><difficult>0</difficult><bndbox><xmin>391</xmin><ymin>386</ymin><xmax>412</xmax><ymax>403</ymax></bndbox></object><object><name>3.0</name><pose>Unspecified</pose><truncated>0</truncated><difficult>0</difficult><bndbox><xmin>459</xmin><ymin>111</ymin><xmax>483</xmax><ymax>139</ymax></bndbox></object><object><name>3.0</name><pose>Unspecified</pose><truncated>0</truncated><difficult>0</difficult><bndbox><xmin>148</xmin><ymin>207</ymin><xmax>176</xmax><ymax>264</ymax></bndbox></object></annotation>