<annotation><folder>Tomato_Village_resized 640x640/train/pascal_voc</folder><filename>IMG20220325090644_aug3.jpg</filename><path>./imagesIMG20220325090644_aug3.jpg</path><source><database>Unknown</database></source><size><width>640</width><height>640</height><depth>3</depth></size><segmented>0</segmented><object><name>7.0</name><pose>Unspecified</pose><truncated>0</truncated><difficult>0</difficult><bndbox><xmin>183</xmin><ymin>518</ymin><xmax>293</xmax><ymax>599</ymax></bndbox></object><object><name>7.0</name><pose>Unspecified</pose><truncated>0</truncated><difficult>0</difficult><bndbox><xmin>518</xmin><ymin>441</ymin><xmax>640</xmax><ymax>538</ymax></bndbox></object><object><name>7.0</name><pose>Unspecified</pose><truncated>0</truncated><difficult>0</difficult><bndbox><xmin>311</xmin><ymin>547</ymin><xmax>436</xmax><ymax>640</ymax></bndbox></object><object><name>7.0</name><pose>Unspecified</pose><truncated>0</truncated><difficult>0</difficult><bndbox><xmin>245</xmin><ymin>589</ymin><xmax>296</xmax><ymax>640</ymax></bndbox></object><object><name>7.0</name><pose>Unspecified</pose><truncated>0</truncated><difficult>0</difficult><bndbox><xmin>154</xmin><ymin>363</ymin><xmax>229</xmax><ymax>443</ymax></bndbox></object><object><name>7.0</name><pose>Unspecified</pose><truncated>0</truncated><difficult>0</difficult><bndbox><xmin>340</xmin><ymin>451</ymin><xmax>397</xmax><ymax>509</ymax></bndbox></object><object><name>7.0</name><pose>Unspecified</pose><truncated>0</truncated><difficult>0</difficult><bndbox><xmin>322</xmin><ymin>350</ymin><xmax>404</xmax><ymax>395</ymax></bndbox></object><object><name>4.0</name><pose>Unspecified</pose><truncated>0</truncated><difficult>0</difficult><bndbox><xmin>55</xmin><ymin>185</ymin><xmax>185</xmax><ymax>245</ymax></bndbox></object><object><name>7.0</name><pose>Unspecified</pose><truncated>0</truncated><difficult>0</difficult><bndbox><xmin>94</xmin><ymin>239</ymin><xmax>162</xmax><ymax>264</ymax></bndbox></object><object><name>4.0</name><pose>Unspecified</pose><truncated>0</truncated><difficult>0</difficult><bndbox><xmin>94</xmin><ymin>341</ymin><xmax>234</xmax><ymax>517</ymax></bndbox></object><object><name>4.0</name><pose>Unspecified</pose><truncated>0</truncated><difficult>0</difficult><bndbox><xmin>312</xmin><ymin>346</ymin><xmax>429</xmax><ymax>404</ymax></bndbox></object><object><name>4.0</name><pose>Unspecified</pose><truncated>0</truncated><difficult>0</difficult><bndbox><xmin>489</xmin><ymin>425</ymin><xmax>640</xmax><ymax>546</ymax></bndbox></object><object><name>4.0</name><pose>Unspecified</pose><truncated>0</truncated><difficult>0</difficult><bndbox><xmin>294</xmin><ymin>528</ymin><xmax>443</xmax><ymax>640</ymax></bndbox></object></annotation>