<annotation><folder>Tomato_Village_resized 640x640/train/pascal_voc</folder><filename>IMG20220325092448_aug3.jpg</filename><path>./imagesIMG20220325092448_aug3.jpg</path><source><database>Unknown</database></source><size><width>640</width><height>640</height><depth>3</depth></size><segmented>0</segmented><object><name>3.0</name><pose>Unspecified</pose><truncated>0</truncated><difficult>0</difficult><bndbox><xmin>238</xmin><ymin>436</ymin><xmax>269</xmax><ymax>453</ymax></bndbox></object><object><name>3.0</name><pose>Unspecified</pose><truncated>0</truncated><difficult>0</difficult><bndbox><xmin>161</xmin><ymin>392</ymin><xmax>195</xmax><ymax>449</ymax></bndbox></object><object><name>3.0</name><pose>Unspecified</pose><truncated>0</truncated><difficult>0</difficult><bndbox><xmin>275</xmin><ymin>379</ymin><xmax>307</xmax><ymax>397</ymax></bndbox></object><object><name>3.0</name><pose>Unspecified</pose><truncated>0</truncated><difficult>0</difficult><bndbox><xmin>153</xmin><ymin>310</ymin><xmax>206</xmax><ymax>347</ymax></bndbox></object><object><name>3.0</name><pose>Unspecified</pose><truncated>0</truncated><difficult>0</difficult><bndbox><xmin>195</xmin><ymin>444</ymin><xmax>233</xmax><ymax>464</ymax></bndbox></object><object><name>3.0</name><pose>Unspecified</pose><truncated>0</truncated><difficult>0</difficult><bndbox><xmin>411</xmin><ymin>172</ymin><xmax>455</xmax><ymax>188</ymax></bndbox></object><object><name>3.0</name><pose>Unspecified</pose><truncated>0</truncated><difficult>0</difficult><bndbox><xmin>482</xmin><ymin>407</ymin><xmax>503</xmax><ymax>426</ymax></bndbox></object><object><name>3.0</name><pose>Unspecified</pose><truncated>0</truncated><difficult>0</difficult><bndbox><xmin>136</xmin><ymin>436</ymin><xmax>167</xmax><ymax>464</ymax></bndbox></object><object><name>3.0</name><pose>Unspecified</pose><truncated>0</truncated><difficult>0</difficult><bndbox><xmin>0</xmin><ymin>331</ymin><xmax>49</xmax><ymax>363</ymax></bndbox></object><object><name>3.0</name><pose>Unspecified</pose><truncated>0</truncated><difficult>0</difficult><bndbox><xmin>0</xmin><ymin>456</ymin><xmax>9</xmax><ymax>484</ymax></bndbox></object><object><name>3.0</name><pose>Unspecified</pose><truncated>0</truncated><difficult>0</difficult><bndbox><xmin>0</xmin><ymin>177</ymin><xmax>26</xmax><ymax>222</ymax></bndbox></object></annotation>