<annotation><folder>Tomato_Village_resized 640x640/train/pascal_voc</folder><filename>IMG20220324084955_aug7.jpg</filename><path>./imagesIMG20220324084955_aug7.jpg</path><source><database>Unknown</database></source><size><width>640</width><height>640</height><depth>3</depth></size><segmented>0</segmented><object><name>3.0</name><pose>Unspecified</pose><truncated>0</truncated><difficult>0</difficult><bndbox><xmin>458</xmin><ymin>230</ymin><xmax>554</xmax><ymax>368</ymax></bndbox></object><object><name>3.0</name><pose>Unspecified</pose><truncated>0</truncated><difficult>0</difficult><bndbox><xmin>472</xmin><ymin>594</ymin><xmax>524</xmax><ymax>640</ymax></bndbox></object><object><name>3.0</name><pose>Unspecified</pose><truncated>0</truncated><difficult>0</difficult><bndbox><xmin>132</xmin><ymin>269</ymin><xmax>196</xmax><ymax>323</ymax></bndbox></object><object><name>3.0</name><pose>Unspecified</pose><truncated>0</truncated><difficult>0</difficult><bndbox><xmin>51</xmin><ymin>176</ymin><xmax>144</xmax><ymax>245</ymax></bndbox></object><object><name>3.0</name><pose>Unspecified</pose><truncated>0</truncated><difficult>0</difficult><bndbox><xmin>274</xmin><ymin>74</ymin><xmax>353</xmax><ymax>131</ymax></bndbox></object><object><name>7.0</name><pose>Unspecified</pose><truncated>0</truncated><difficult>0</difficult><bndbox><xmin>170</xmin><ymin>92</ymin><xmax>459</xmax><ymax>278</ymax></bndbox></object><object><name>7.0</name><pose>Unspecified</pose><truncated>0</truncated><difficult>0</difficult><bndbox><xmin>456</xmin><ymin>21</ymin><xmax>640</xmax><ymax>154</ymax></bndbox></object><object><name>7.0</name><pose>Unspecified</pose><truncated>0</truncated><difficult>0</difficult><bndbox><xmin>562</xmin><ymin>179</ymin><xmax>610</xmax><ymax>316</ymax></bndbox></object></annotation>