<annotation><folder>Tomato_Village_resized 640x640/train/pascal_voc</folder><filename>Jaipur_Pots (432)_aug6.jpg</filename><path>./imagesJaipur_Pots (432)_aug6.jpg</path><source><database>Unknown</database></source><size><width>640</width><height>640</height><depth>3</depth></size><segmented>0</segmented><object><name>3.0</name><pose>Unspecified</pose><truncated>0</truncated><difficult>0</difficult><bndbox><xmin>133</xmin><ymin>582</ymin><xmax>222</xmax><ymax>635</ymax></bndbox></object><object><name>3.0</name><pose>Unspecified</pose><truncated>0</truncated><difficult>0</difficult><bndbox><xmin>292</xmin><ymin>597</ymin><xmax>378</xmax><ymax>638</ymax></bndbox></object><object><name>3.0</name><pose>Unspecified</pose><truncated>0</truncated><difficult>0</difficult><bndbox><xmin>391</xmin><ymin>472</ymin><xmax>552</xmax><ymax>609</ymax></bndbox></object><object><name>3.0</name><pose>Unspecified</pose><truncated>0</truncated><difficult>0</difficult><bndbox><xmin>373</xmin><ymin>93</ymin><xmax>456</xmax><ymax>257</ymax></bndbox></object><object><name>3.0</name><pose>Unspecified</pose><truncated>0</truncated><difficult>0</difficult><bndbox><xmin>506</xmin><ymin>400</ymin><xmax>552</xmax><ymax>437</ymax></bndbox></object><object><name>3.0</name><pose>Unspecified</pose><truncated>0</truncated><difficult>0</difficult><bndbox><xmin>352</xmin><ymin>96</ymin><xmax>630</xmax><ymax>514</ymax></bndbox></object><object><name>3.0</name><pose>Unspecified</pose><truncated>0</truncated><difficult>0</difficult><bndbox><xmin>11</xmin><ymin>333</ymin><xmax>316</xmax><ymax>587</ymax></bndbox></object></annotation>