<annotation><folder>Tomato_Village_resized 640x640/train/pascal_voc</folder><filename>Jaipur_Pots (312)_aug1.jpg</filename><path>./imagesJaipur_Pots (312)_aug1.jpg</path><source><database>Unknown</database></source><size><width>640</width><height>640</height><depth>3</depth></size><segmented>0</segmented><object><name>3.0</name><pose>Unspecified</pose><truncated>0</truncated><difficult>0</difficult><bndbox><xmin>3</xmin><ymin>21</ymin><xmax>42</xmax><ymax>118</ymax></bndbox></object><object><name>3.0</name><pose>Unspecified</pose><truncated>0</truncated><difficult>0</difficult><bndbox><xmin>136</xmin><ymin>455</ymin><xmax>175</xmax><ymax>501</ymax></bndbox></object><object><name>3.0</name><pose>Unspecified</pose><truncated>0</truncated><difficult>0</difficult><bndbox><xmin>130</xmin><ymin>342</ymin><xmax>231</xmax><ymax>477</ymax></bndbox></object><object><name>3.0</name><pose>Unspecified</pose><truncated>0</truncated><difficult>0</difficult><bndbox><xmin>187</xmin><ymin>255</ymin><xmax>280</xmax><ymax>303</ymax></bndbox></object><object><name>3.0</name><pose>Unspecified</pose><truncated>0</truncated><difficult>0</difficult><bndbox><xmin>380</xmin><ymin>271</ymin><xmax>494</xmax><ymax>330</ymax></bndbox></object><object><name>3.0</name><pose>Unspecified</pose><truncated>0</truncated><difficult>0</difficult><bndbox><xmin>314</xmin><ymin>135</ymin><xmax>435</xmax><ymax>252</ymax></bndbox></object><object><name>3.0</name><pose>Unspecified</pose><truncated>0</truncated><difficult>0</difficult><bndbox><xmin>431</xmin><ymin>177</ymin><xmax>459</xmax><ymax>218</ymax></bndbox></object><object><name>3.0</name><pose>Unspecified</pose><truncated>0</truncated><difficult>0</difficult><bndbox><xmin>293</xmin><ymin>511</ymin><xmax>390</xmax><ymax>640</ymax></bndbox></object></annotation>