<annotation><folder>Tomato_Village_resized 640x640/train/pascal_voc</folder><filename>Jaipur_Pots (137)_aug6.jpg</filename><path>./imagesJaipur_Pots (137)_aug6.jpg</path><source><database>Unknown</database></source><size><width>640</width><height>640</height><depth>3</depth></size><segmented>0</segmented><object><name>3.0</name><pose>Unspecified</pose><truncated>0</truncated><difficult>0</difficult><bndbox><xmin>120</xmin><ymin>299</ymin><xmax>249</xmax><ymax>436</ymax></bndbox></object><object><name>3.0</name><pose>Unspecified</pose><truncated>0</truncated><difficult>0</difficult><bndbox><xmin>55</xmin><ymin>224</ymin><xmax>175</xmax><ymax>278</ymax></bndbox></object><object><name>3.0</name><pose>Unspecified</pose><truncated>0</truncated><difficult>0</difficult><bndbox><xmin>242</xmin><ymin>311</ymin><xmax>512</xmax><ymax>572</ymax></bndbox></object><object><name>3.0</name><pose>Unspecified</pose><truncated>0</truncated><difficult>0</difficult><bndbox><xmin>391</xmin><ymin>251</ymin><xmax>465</xmax><ymax>348</ymax></bndbox></object><object><name>3.0</name><pose>Unspecified</pose><truncated>0</truncated><difficult>0</difficult><bndbox><xmin>228</xmin><ymin>3</ymin><xmax>414</xmax><ymax>247</ymax></bndbox></object></annotation>