<annotation><folder>Tomato_Village_resized 640x640/train/pascal_voc</folder><filename>Jaipur_Pots (580)_aug5.jpg</filename><path>./imagesJaipur_Pots (580)_aug5.jpg</path><source><database>Unknown</database></source><size><width>640</width><height>640</height><depth>3</depth></size><segmented>0</segmented><object><name>3.0</name><pose>Unspecified</pose><truncated>0</truncated><difficult>0</difficult><bndbox><xmin>367</xmin><ymin>288</ymin><xmax>412</xmax><ymax>368</ymax></bndbox></object><object><name>3.0</name><pose>Unspecified</pose><truncated>0</truncated><difficult>0</difficult><bndbox><xmin>597</xmin><ymin>37</ymin><xmax>606</xmax><ymax>71</ymax></bndbox></object><object><name>3.0</name><pose>Unspecified</pose><truncated>0</truncated><difficult>0</difficult><bndbox><xmin>545</xmin><ymin>60</ymin><xmax>567</xmax><ymax>133</ymax></bndbox></object><object><name>3.0</name><pose>Unspecified</pose><truncated>0</truncated><difficult>0</difficult><bndbox><xmin>483</xmin><ymin>148</ymin><xmax>520</xmax><ymax>212</ymax></bndbox></object><object><name>3.0</name><pose>Unspecified</pose><truncated>0</truncated><difficult>0</difficult><bndbox><xmin>311</xmin><ymin>425</ymin><xmax>365</xmax><ymax>592</ymax></bndbox></object><object><name>5.0</name><pose>Unspecified</pose><truncated>0</truncated><difficult>0</difficult><bndbox><xmin>553</xmin><ymin>20</ymin><xmax>599</xmax><ymax>198</ymax></bndbox></object><object><name>5.0</name><pose>Unspecified</pose><truncated>0</truncated><difficult>0</difficult><bndbox><xmin>483</xmin><ymin>2</ymin><xmax>561</xmax><ymax>157</ymax></bndbox></object><object><name>5.0</name><pose>Unspecified</pose><truncated>0</truncated><difficult>0</difficult><bndbox><xmin>385</xmin><ymin>127</ymin><xmax>431</xmax><ymax>254</ymax></bndbox></object><object><name>5.0</name><pose>Unspecified</pose><truncated>0</truncated><difficult>0</difficult><bndbox><xmin>392</xmin><ymin>87</ymin><xmax>422</xmax><ymax>133</ymax></bndbox></object><object><name>5.0</name><pose>Unspecified</pose><truncated>0</truncated><difficult>0</difficult><bndbox><xmin>358</xmin><ymin>168</ymin><xmax>390</xmax><ymax>220</ymax></bndbox></object><object><name>5.0</name><pose>Unspecified</pose><truncated>0</truncated><difficult>0</difficult><bndbox><xmin>350</xmin><ymin>214</ymin><xmax>406</xmax><ymax>355</ymax></bndbox></object><object><name>5.0</name><pose>Unspecified</pose><truncated>0</truncated><difficult>0</difficult><bndbox><xmin>299</xmin><ymin>322</ymin><xmax>368</xmax><ymax>588</ymax></bndbox></object></annotation>