<annotation><folder>Tomato_Village_resized 640x640/train/pascal_voc</folder><filename>Jaipur_Pots (639)_aug7.jpg</filename><path>./imagesJaipur_Pots (639)_aug7.jpg</path><source><database>Unknown</database></source><size><width>640</width><height>640</height><depth>3</depth></size><segmented>0</segmented><object><name>3.0</name><pose>Unspecified</pose><truncated>0</truncated><difficult>0</difficult><bndbox><xmin>403</xmin><ymin>0</ymin><xmax>640</xmax><ymax>130</ymax></bndbox></object><object><name>3.0</name><pose>Unspecified</pose><truncated>0</truncated><difficult>0</difficult><bndbox><xmin>524</xmin><ymin>120</ymin><xmax>640</xmax><ymax>246</ymax></bndbox></object><object><name>3.0</name><pose>Unspecified</pose><truncated>0</truncated><difficult>0</difficult><bndbox><xmin>207</xmin><ymin>131</ymin><xmax>364</xmax><ymax>301</ymax></bndbox></object><object><name>3.0</name><pose>Unspecified</pose><truncated>0</truncated><difficult>0</difficult><bndbox><xmin>215</xmin><ymin>228</ymin><xmax>478</xmax><ymax>547</ymax></bndbox></object><object><name>3.0</name><pose>Unspecified</pose><truncated>0</truncated><difficult>0</difficult><bndbox><xmin>520</xmin><ymin>295</ymin><xmax>640</xmax><ymax>536</ymax></bndbox></object></annotation>